lintaosp/__init__.py
lintaosp/__version__.py
lintaosp/main.py
lintaosp/aosp/__init__.py
lintaosp/aosp/abstract.py
lintaosp/aosp/aosp.py
lintaosp/aosp/sdk.py
lintaosp/cmd/__init__.py
lintaosp/cmd/argument.py
lintaosp/cmd/banner.py
lintaosp/config/__init__.py
lintaosp/config/config.py
lintaosp/config/config.yml
lintaosp/lint/__init__.py
lintaosp/lint/lint.py
lintaosp/lint/lint_pb2.py
lintaosp/lint/lint_pb2_grpc.py
lintaosp/logger/__init__.py
lintaosp/logger/logger.py
lintaosp/printer/__init__.py
lintaosp/printer/printer.py
lintaosp/proto/__init__.py
lintaosp/proto/proto.py
lintaosp/queue/__init__.py
lintaosp/queue/queue.py
lintaosp-1.2.4.dist-info/LICENSE
lintaosp-1.2.4.dist-info/METADATA
lintaosp-1.2.4.dist-info/WHEEL
lintaosp-1.2.4.dist-info/entry_points.txt
lintaosp-1.2.4.dist-info/top_level.txt
lintaosp-1.2.4.dist-info/RECORD
