Metadata-Version: 2.1
Name: lintaosp
Version: 1.2.4
Summary: Lint AOSP
Home-page: https://github.com/craftslab/lintaosp
Author: Jia Jia
Author-email: angersax@sina.com
License: Apache-2.0
Download-URL: https://github.com/craftslab/lintaosp/archive/v1.2.4.tar.gz
Keywords: lint,aosp
Platform: UNKNOWN
Classifier: Development Status :: 3 - Alpha
Classifier: Intended Audience :: Developers
Classifier: Programming Language :: Python :: 3
Classifier: License :: OSI Approved :: Apache Software License
Classifier: Operating System :: OS Independent
Requires-Dist: black
Requires-Dist: colorama
Requires-Dist: coverage
Requires-Dist: coveralls
Requires-Dist: flake8
Requires-Dist: grpcio
Requires-Dist: grpcio-tools
Requires-Dist: hypothesis
Requires-Dist: mypy
Requires-Dist: openpyxl
Requires-Dist: pre-commit
Requires-Dist: pytest
Requires-Dist: pyyaml
Requires-Dist: setuptools
Requires-Dist: twine
Requires-Dist: wheel
